{
    "name": "Contact",
    "fields": [
        {
            "fieldName": "email",
            "fieldType": "String",
            "fieldValidateRules": [
                "required"
            ]
        },
        {
            "fieldName": "gender",
            "fieldType": "Gender",
            "fieldValues": "UNKNOW,MALE,FEMALE"
        },
        {
            "fieldName": "fullName",
            "fieldType": "String"
        },
        {
            "fieldName": "lastName",
            "fieldType": "String"
        },
        {
            "fieldName": "firstName",
            "fieldType": "String"
        },
        {
            "fieldName": "attributes",
            "fieldType": "String"
        }
    ],
    "relationships": [
        {
            "relationshipType": "many-to-one",
            "relationshipName": "list",
            "otherEntityName": "contactList",
            "otherEntityField": "id"
        }
    ],
    "changelogDate": "20180906154758",
    "entityTableName": "contact",
    "dto": "mapstruct",
    "pagination": "pagination",
    "service": "serviceImpl",
    "jpaMetamodelFiltering": false,
    "fluentMethods": true,
    "clientRootFolder": "",
    "applications": "*",
    "enableEntityAudit": true
}
