{
    "name": "Contract",
    "fields": [
        {
            "fieldName": "uuid",
            "fieldType": "String",
            "fieldValidateRules": [
                "required"
            ]
        },
        {
            "fieldName": "name",
            "fieldType": "String",
            "fieldValidateRules": [
                "required"
            ]
        },
        {
            "fieldName": "subject",
            "fieldType": "String",
            "fieldValidateRules": [
                "required"
            ]
        },
        {
            "fieldName": "status",
            "fieldType": "Status",
            "fieldValues": "ANY,DRAFT,PENDING,CANCELED,DECLINED,EXPIRED,SIGNED,COMPLETED,VIEWED"
        },
        {
            "fieldName": "description",
            "fieldType": "String"
        },
        {
            "fieldName": "content",
            "fieldType": "String"
        },
        {
            "fieldName": "requestAcess",
            "fieldType": "Boolean"
        },
        {
            "fieldName": "lastActivityAt",
            "fieldType": "LocalDate",
            "fieldValidateRules": [
                "required"
            ]
        },
        {
            "fieldName": "expiresAt",
            "fieldType": "LocalDate"
        },
        {
            "fieldName": "type",
            "fieldType": "String"
        }
    ],
    "relationships": [
        {
            "relationshipType": "one-to-many",
            "relationshipName": "requests",
            "otherEntityName": "signatureRequest",
            "otherEntityRelationshipName": "contract"
        },
        {
            "relationshipType": "many-to-one",
            "relationshipName": "project",
            "otherEntityName": "project",
            "otherEntityField": "id"
        }
    ],
    "changelogDate": "20180906154753",
    "entityTableName": "contract",
    "dto": "mapstruct",
    "pagination": "pagination",
    "service": "serviceImpl",
    "jpaMetamodelFiltering": false,
    "fluentMethods": true,
    "clientRootFolder": "",
    "applications": "*",
    "enableEntityAudit": true
}
